runefumbler/__init__.py
runefumbler/fumbler.py
runefumbler-0.1.5.dist-info/entry_points.txt
runefumbler-0.1.5.dist-info/METADATA
runefumbler-0.1.5.dist-info/WHEEL
runefumbler-0.1.5.dist-info/RECORD
