Metadata-Version: 2.1
Name: runefumbler
Version: 0.1.5
Summary: Don't be fumblin' no trades now
Author: None
Requires-Python: >=3.11,<4.0
Classifier: Programming Language :: Python :: 3
Classifier: Programming Language :: Python :: 3.11
Requires-Dist: pyautogui (>=0.9.54,<0.10.0)
Requires-Dist: pywin32 (>=306,<307)
